self_code_adk/__init__.py
self_code_adk/agent.py
self_code_adk/agent_test.py
self_code_adk-0.1.6.dist-info/licenses/LICENSE
self_code_adk-0.1.6.dist-info/METADATA
self_code_adk-0.1.6.dist-info/WHEEL
self_code_adk-0.1.6.dist-info/top_level.txt
self_code_adk-0.1.6.dist-info/RECORD
