Metadata-Version: 2.4
Name: self-code-adk
Version: 0.1.6
Summary: ADK agent which help in analysing currently running multiagent app
Author: Marcin <n0npax> Niemira
Maintainer: Marcin <n0npax> Niemira
License-Expression: MIT
Project-URL: Homepage, https://github.com/n0npax/self-code-adk
Project-URL: Documentation, https://github.com/n0npax/self-code-adk
Project-URL: Repository, https://github.com/n0npax/self-code-adk
Keywords: adk,agent,code-analyzer
Requires-Python: >=3.12
License-File: LICENSE
Requires-Dist: google-adk>=0.3.0
Dynamic: license-file
